{
  "name": "bau_macc-rsd-RSD-DEEP",
  "data": [
    {
      "seriesName": "RSD_BLD-DET-GAS",
      "seriesValues": [
        [
          2019,
          2.611602105392527e-06
        ],
        [
          2020,
          9.444460060284763e-06
        ],
        [
          2021,
          41.337928312452206
        ],
        [
          2022,
          41.86016253894942
        ],
        [
          2023,
          42.49106284032008
        ],
        [
          2024,
          42.85690758613175
        ],
        [
          2025,
          42.83636475454669
        ],
        [
          2026,
          43.33264922351734
        ],
        [
          2027,
          43.60463104669533
        ],
        [
          2028,
          44.349192104305665
        ],
        [
          2029,
          44.61224061750088
        ],
        [
          2030,
          44.71880668109427
        ],
        [
          2031,
          39.67120240740069
        ],
        [
          2032,
          33.0785633061497
        ],
        [
          2033,
          28.12489541309722
        ],
        [
          2034,
          30.118890991749346
        ],
        [
          2035,
          29.87398360153763
        ],
        [
          2036,
          25.55739420527348
        ],
        [
          2037,
          5.065492503162207
        ],
        [
          2038,
          4.656819480249082
        ],
        [
          2039,
          54.182468203127996
        ],
        [
          2040,
          2.0128581098899647
        ],
        [
          2041,
          41.51916459505289
        ],
        [
          2042,
          42.01561527361341
        ],
        [
          2043,
          43.515284003286325
        ],
        [
          2044,
          45.306774862069574
        ],
        [
          2045,
          45.00267396065114
        ],
        [
          2046,
          45.212795208840284
        ],
        [
          2047,
          45.18270850170749
        ],
        [
          2048,
          45.616640834409594
        ],
        [
          2049,
          45.54126160242845
        ],
        [
          2050,
          45.31073008186513
        ],
        [
          2051,
          1.783259484968201e-05
        ]
      ]
    },
    {
      "seriesName": "RSD_BLD-DET-HP",
      "seriesValues": [
        [
          2019,
          58.29626016358741
        ],
        [
          2051,
          39.93304737742741
        ]
      ]
    },
    {
      "seriesName": "RSD_BLD-DET-OTH",
      "seriesValues": [
        [
          2019,
          0.6272794490682645
        ],
        [
          2020,
          48.13213744880167
        ],
        [
          2021,
          0.04645737465170872
        ],
        [
          2022,
          2.3980376407585054e-05
        ],
        [
          2023,
          2.1454826810874447e-05
        ],
        [
          2024,
          0.5777475108140054
        ],
        [
          2025,
          1.7008798452796532
        ],
        [
          2026,
          3.1834977512135736
        ],
        [
          2027,
          1.5840097919250662
        ],
        [
          2028,
          1.637018483866437
        ],
        [
          2029,
          3.7648272281571087
        ],
        [
          2030,
          3.769691691339646
        ],
        [
          2031,
          3.7749851578859723
        ],
        [
          2032,
          13.100808273932305
        ],
        [
          2033,
          17.991693729543595
        ],
        [
          2034,
          15.814542562921945
        ],
        [
          2035,
          15.670252090736719
        ],
        [
          2036,
          19.602754053404222
        ],
        [
          2037,
          39.97840559965383
        ],
        [
          2038,
          40.21261353324697
        ],
        [
          2039,
          10.489254763995321
        ],
        [
          2040,
          49.45206389797019
        ],
        [
          2041,
          2.098095422186831e-05
        ],
        [
          2042,
          2.135172697548739e-05
        ],
        [
          2043,
          2.1711890374916756e-05
        ],
        [
          2044,
          2.2054951031435118e-05
        ],
        [
          2045,
          2.250926357310556e-05
        ],
        [
          2046,
          2.1847125843637127
        ],
        [
          2047,
          1.125589813200154
        ],
        [
          2048,
          1.1831283177728553
        ],
        [
          2049,
          3.3143697552810654
        ],
        [
          2050,
          3.3243517796548328
        ],
        [
          2051,
          3.3342270079792655
        ]
      ]
    },
    {
      "seriesName": "RSD_BLD-DET-ELC",
      "seriesValues": [
        [
          2021,
          6.26982517613738e-06
        ],
        [
          2022,
          6.9747879724519e-06
        ],
        [
          2023,
          8.28949959935658e-06
        ],
        [
          2024,
          8.62985498152402e-06
        ],
        [
          2025,
          9.06917530132122e-06
        ],
        [
          2026,
          9.52053673637892e-06
        ],
        [
          2027,
          1.01134188911071e-05
        ],
        [
          2028,
          1.07866693154066e-05
        ],
        [
          2029,
          1.15914370935641e-05
        ],
        [
          2030,
          1.25150299785372e-05
        ],
        [
          2031,
          1.3634127925776e-05
        ],
        [
          2032,
          1.42571462294806e-05
        ],
        [
          2033,
          1.49436417671915e-05
        ],
        [
          2034,
          1.56445159108874e-05
        ],
        [
          2035,
          1.63532747336101e-05
        ],
        [
          2036,
          1.70407638536428e-05
        ],
        [
          2037,
          1.7851874254733e-05
        ],
        [
          2038,
          2.00676567359129e-05
        ],
        [
          2039,
          2.41761653263525e-05
        ],
        [
          2040,
          6.32646717993061e-06
        ],
        [
          2041,
          1.71106548327608e-05
        ],
        [
          2042,
          1.74812508094028e-05
        ],
        [
          2043,
          1.779555441638e-05
        ],
        [
          2044,
          1.81014045419918e-05
        ],
        [
          2045,
          1.83460258530097e-05
        ],
        [
          2046,
          1.85700991960043e-05
        ],
        [
          2047,
          1.83372969540726e-05
        ],
        [
          2048,
          1.79218242054567e-05
        ],
        [
          2049,
          1.7604666760973e-05
        ],
        [
          2050,
          1.63686410778274e-05
        ],
        [
          2051,
          0.0
        ]
      ]
    }
  ]
}