{
  "name": "bau_macc-ind-elc",
  "data": [
    {
      "seriesName": "RSD_BLD-XXX_NRGSRV-CD",
      "seriesValues": [
        [
          2018,
          1.752821942182699
        ],
        [
          2019,
          1.8080585475315034
        ],
        [
          2020,
          1.8394989950958696
        ],
        [
          2021,
          1.8703237852178523
        ],
        [
          2022,
          1.900140795998694
        ],
        [
          2023,
          1.9296542715761422
        ],
        [
          2024,
          1.958551687267024
        ],
        [
          2025,
          1.9861279861137269
        ],
        [
          2026,
          2.013871054823778
        ],
        [
          2027,
          2.041389072718897
        ],
        [
          2028,
          2.0700141625977952
        ],
        [
          2029,
          2.098649557620375
        ],
        [
          2030,
          2.12698191772878
        ],
        [
          2031,
          2.1554545249379533
        ],
        [
          2032,
          2.183551599017769
        ],
        [
          2033,
          2.2118169430278836
        ],
        [
          2034,
          2.2399371694899273
        ],
        [
          2035,
          2.2673642593285233
        ],
        [
          2036,
          2.294098361801417
        ],
        [
          2037,
          2.320843664509226
        ],
        [
          2038,
          2.347443250105692
        ],
        [
          2039,
          2.373114724503394
        ],
        [
          2040,
          2.39777930248907
        ],
        [
          2041,
          2.404437283169409
        ],
        [
          2042,
          2.425835892869481
        ],
        [
          2043,
          2.4496249535193155
        ],
        [
          2044,
          2.47295503043507
        ],
        [
          2045,
          2.4957905564926994
        ],
        [
          2046,
          2.518113727585717
        ],
        [
          2047,
          2.539868242849268
        ],
        [
          2048,
          2.561017340018016
        ],
        [
          2049,
          2.5814644349144467
        ],
        [
          2050,
          2.6012035519766212
        ],
        [
          2051,
          2.620238784041821
        ]
      ]
    },
    {
      "seriesName": "RSD_BLD-XXX_NRGSRV-CK",
      "seriesValues": [
        [
          2018,
          2.7611554513679644
        ],
        [
          2019,
          2.9157456166456046
        ],
        [
          2020,
          3.023506301326788
        ],
        [
          2021,
          3.130055201482405
        ],
        [
          2022,
          3.2346210061941236
        ],
        [
          2023,
          3.338589094850563
        ],
        [
          2024,
          3.441345058410368
        ],
        [
          2025,
          3.541501131340957
        ],
        [
          2026,
          3.6419853862562466
        ],
        [
          2027,
          3.742026748477391
        ],
        [
          2028,
          3.8442467890444414
        ],
        [
          2029,
          3.9464871114155797
        ],
        [
          2030,
          4.048131053509922
        ],
        [
          2031,
          4.150051018393316
        ],
        [
          2032,
          4.2512319795536
        ],
        [
          2033,
          4.352744070652325
        ],
        [
          2034,
          4.408083257435636
        ],
        [
          2035,
          4.462058327729934
        ],
        [
          2036,
          4.514669690448783
        ],
        [
          2037,
          4.567303076493802
        ],
        [
          2038,
          4.619649789489812
        ],
        [
          2039,
          4.6701698387435115
        ],
        [
          2040,
          4.718708524542521
        ],
        [
          2041,
          4.731811064998333
        ],
        [
          2042,
          4.773922437138445
        ],
        [
          2043,
          4.820738098153278
        ],
        [
          2044,
          4.866650512060362
        ],
        [
          2045,
          4.911589634833494
        ],
        [
          2046,
          4.955520507720854
        ],
        [
          2047,
          4.998332329708244
        ],
        [
          2048,
          5.039952657561519
        ],
        [
          2049,
          5.080191649658192
        ],
        [
          2050,
          5.119037249315192
        ],
        [
          2051,
          5.15649757917597
        ]
      ]
    },
    {
      "seriesName": "RSD_BLD-XXX_NRGSRV-CW",
      "seriesValues": [
        [
          2018,
          1.1268114283822492
        ],
        [
          2019,
          1.1623205902895175
        ],
        [
          2020,
          1.182532259229638
        ],
        [
          2021,
          1.2023481489178327
        ],
        [
          2022,
          1.221516181642486
        ],
        [
          2023,
          1.240489084566144
        ],
        [
          2024,
          1.259065950567326
        ],
        [
          2025,
          1.2767935291860932
        ],
        [
          2026,
          1.2946283167484036
        ],
        [
          2027,
          1.3123184291310162
        ],
        [
          2028,
          1.330720228901742
        ],
        [
          2029,
          1.349128653392271
        ],
        [
          2030,
          1.367342270185562
        ],
        [
          2031,
          1.3856460456147037
        ],
        [
          2032,
          1.4037084074632808
        ],
        [
          2033,
          1.421878942580326
        ],
        [
          2034,
          1.4399561880680691
        ],
        [
          2035,
          1.4575878467851928
        ],
        [
          2036,
          1.4747740146826032
        ],
        [
          2037,
          1.4919673827134046
        ],
        [
          2038,
          1.5090670756815459
        ],
        [
          2039,
          1.5255701271534856
        ],
        [
          2040,
          1.541425889402447
        ],
        [
          2041,
          1.545706009879609
        ],
        [
          2042,
          1.5594622262858961
        ],
        [
          2043,
          1.5747551575088945
        ],
        [
          2044,
          1.5897530284611456
        ],
        [
          2045,
          1.6044329746168506
        ],
        [
          2046,
          1.6187835505060517
        ],
        [
          2047,
          1.6327685628032476
        ],
        [
          2048,
          1.6463643786770852
        ],
        [
          2049,
          1.6595089084460406
        ],
        [
          2050,
          1.6721983106900442
        ],
        [
          2051,
          1.6844352165134309
        ]
      ]
    },
    {
      "seriesName": "RSD_BLD-XXX_NRGSRV-DW",
      "seriesValues": [
        [
          2018,
          1.2125521732445999
        ],
        [
          2019,
          1.2507632797392345
        ],
        [
          2020,
          1.2725128843583835
        ],
        [
          2021,
          1.2938365943138361
        ],
        [
          2022,
          1.314463150876314
        ],
        [
          2023,
          1.3348797300549233
        ],
        [
          2024,
          1.3548701371969427
        ],
        [
          2025,
          1.3739466334254562
        ],
        [
          2026,
          1.3931384962842401
        ],
        [
          2027,
          1.4121746754147488
        ],
        [
          2028,
          1.4319766952933193
        ],
        [
          2029,
          1.4517858439769202
        ],
        [
          2030,
          1.4713853617568493
        ],
        [
          2031,
          1.4910818984794982
        ],
        [
          2032,
          1.5105186521052623
        ],
        [
          2033,
          1.5300718100637503
        ],
        [
          2034,
          1.5495245798466712
        ],
        [
          2035,
          1.5684978575034918
        ],
        [
          2036,
          1.586991746287276
        ],
        [
          2037,
          1.6054933830730107
        ],
        [
          2038,
          1.6238942169224415
        ],
        [
          2039,
          1.6416530099438706
        ],
        [
          2040,
          1.6587152605646327
        ],
        [
          2041,
          1.6633210617148357
        ],
        [
          2042,
          1.6781240089369966
        ],
        [
          2043,
          1.6945806018743683
        ],
        [
          2044,
          1.7107196829696119
        ],
        [
          2045,
          1.7265166479017806
        ],
        [
          2046,
          1.741959180297792
        ],
        [
          2047,
          1.7570083328273305
        ],
        [
          2048,
          1.7716386744050283
        ],
        [
          2049,
          1.7857833908548622
        ],
        [
          2050,
          1.799438348453092
        ],
        [
          2051,
          1.8126063785066147
        ]
      ]
    },
    {
      "seriesName": "RSD_BLD-XXX_NRGSRV-LT",
      "seriesValues": [
        [
          2018,
          4.879741124685987
        ],
        [
          2019,
          4.956926375027643
        ],
        [
          2020,
          4.977937575447085
        ],
        [
          2021,
          4.976884274472598
        ],
        [
          2022,
          4.570414894077659
        ],
        [
          2023,
          4.610290817172237
        ],
        [
          2024,
          4.649738537916907
        ],
        [
          2025,
          4.687574526727658
        ],
        [
          2026,
          4.726381671351733
        ],
        [
          2027,
          4.765155469772773
        ],
        [
          2028,
          4.806141160436454
        ],
        [
          2029,
          4.834930692485142
        ],
        [
          2030,
          4.835211140159708
        ],
        [
          2031,
          4.796977450070308
        ],
        [
          2032,
          3.943088157383879
        ],
        [
          2033,
          3.9714811068858413
        ],
        [
          2034,
          3.9991260508265314
        ],
        [
          2035,
          4.025369897885892
        ],
        [
          2036,
          4.050260677645993
        ],
        [
          2037,
          4.0746855358849405
        ],
        [
          2038,
          4.098474260040532
        ],
        [
          2039,
          4.114131559607259
        ],
        [
          2040,
          4.113720837978195
        ],
        [
          2041,
          4.077366672592621
        ],
        [
          2042,
          3.592532232453625
        ],
        [
          2043,
          3.606330230261496
        ],
        [
          2044,
          3.620332358940027
        ],
        [
          2045,
          3.633741654942457
        ],
        [
          2046,
          3.6465516702889653
        ],
        [
          2047,
          3.658604917392239
        ],
        [
          2048,
          3.6699095794761303
        ],
        [
          2049,
          3.6757695170513935
        ],
        [
          2050,
          3.669990591408609
        ],
        [
          2051,
          3.6545861461121847
        ]
      ]
    },
    {
      "seriesName": "RSD_BLD-XXX_NRGSRV-OE",
      "seriesValues": [
        [
          2018,
          10.843443600153996
        ],
        [
          2019,
          11.185152589255445
        ],
        [
          2020,
          11.379651933162382
        ],
        [
          2021,
          11.570342649080082
        ],
        [
          2022,
          11.754798962421694
        ],
        [
          2023,
          11.93737751963478
        ],
        [
          2024,
          12.116144961614397
        ],
        [
          2025,
          12.28673960768742
        ],
        [
          2026,
          12.458365938501007
        ],
        [
          2027,
          12.628600042378993
        ],
        [
          2028,
          12.805682802538817
        ],
        [
          2029,
          12.98282931322915
        ],
        [
          2030,
          13.158101165692505
        ],
        [
          2031,
          13.33424062569602
        ],
        [
          2032,
          13.508056933400292
        ],
        [
          2033,
          13.6829142056556
        ],
        [
          2034,
          13.856873740432155
        ],
        [
          2035,
          14.026545339630488
        ],
        [
          2036,
          14.191929926251117
        ],
        [
          2037,
          14.357383800622332
        ],
        [
          2038,
          14.521936228443277
        ],
        [
          2039,
          14.680747102332452
        ],
        [
          2040,
          14.83332903539546
        ],
        [
          2041,
          14.874517154108668
        ],
        [
          2042,
          15.006894899820528
        ],
        [
          2043,
          15.154060639341772
        ],
        [
          2044,
          15.298386977941192
        ],
        [
          2045,
          15.439653887532161
        ],
        [
          2046,
          15.577751226895153
        ],
        [
          2047,
          15.712330703303385
        ],
        [
          2048,
          15.843164895154171
        ],
        [
          2049,
          15.969656305838155
        ],
        [
          2050,
          16.09176796893508
        ],
        [
          2051,
          16.209525203852234
        ]
      ]
    },
    {
      "seriesName": "RSD_BLD-XXX_NRGSRV-PF",
      "seriesValues": [
        [
          2018,
          1.1389592682928154
        ],
        [
          2019,
          1.200284991313205
        ],
        [
          2020,
          1.2368451102827143
        ],
        [
          2021,
          1.2706531316729002
        ],
        [
          2022,
          1.3036519701445068
        ],
        [
          2023,
          1.3365574149914279
        ],
        [
          2024,
          1.3689829946021732
        ],
        [
          2025,
          1.4001239869740345
        ],
        [
          2026,
          1.4315838456480892
        ],
        [
          2027,
          1.4629123222340312
        ],
        [
          2028,
          1.4955481413282816
        ],
        [
          2029,
          1.5282777736904192
        ],
        [
          2030,
          1.5607478707924054
        ],
        [
          2031,
          1.591750535919325
        ],
        [
          2032,
          1.6232564649700407
        ],
        [
          2033,
          1.6549035566184473
        ],
        [
          2034,
          1.6863504461630505
        ],
        [
          2035,
          1.7170015898494193
        ],
        [
          2036,
          1.7468587709667525
        ],
        [
          2037,
          1.7766882602299614
        ],
        [
          2038,
          1.8063197929250447
        ],
        [
          2039,
          1.8349053537190052
        ],
        [
          2040,
          1.8623617252173685
        ],
        [
          2041,
          1.8716992452999375
        ],
        [
          2042,
          1.8944752095262045
        ],
        [
          2043,
          1.920562892732496
        ],
        [
          2044,
          1.9464479962334518
        ],
        [
          2045,
          1.9717646560386997
        ],
        [
          2046,
          1.996494815168049
        ],
        [
          2047,
          2.02057896001554
        ],
        [
          2048,
          2.0439787993207887
        ],
        [
          2049,
          2.0665917391144872
        ],
        [
          2050,
          2.0884129699351566
        ],
        [
          2051,
          2.109448524488379
        ]
      ]
    },
    {
      "seriesName": "RSD_BLD-XXX_NRGSRV-RF",
      "seriesValues": [
        [
          2018,
          1.4430682741859997
        ],
        [
          2019,
          1.4885436250209363
        ],
        [
          2020,
          1.5144280070041711
        ],
        [
          2021,
          1.5398055287630097
        ],
        [
          2022,
          1.564353363087441
        ],
        [
          2023,
          1.5886513010747298
        ],
        [
          2024,
          1.6124420483017277
        ],
        [
          2025,
          1.6351451426642418
        ],
        [
          2026,
          1.6579855357986757
        ],
        [
          2027,
          1.6806406484531502
        ],
        [
          2028,
          1.704207194521349
        ],
        [
          2029,
          1.7277822248231176
        ],
        [
          2030,
          1.7511077738849279
        ],
        [
          2031,
          1.7744903275696826
        ],
        [
          2032,
          1.7975070838649445
        ],
        [
          2033,
          1.8206042291024271
        ],
        [
          2034,
          1.8416468814633047
        ],
        [
          2035,
          1.861847237421327
        ],
        [
          2036,
          1.8810240485561445
        ],
        [
          2037,
          1.8997601595350142
        ],
        [
          2038,
          1.9179237749958435
        ],
        [
          2039,
          1.9348946204538096
        ],
        [
          2040,
          1.9506318685044848
        ],
        [
          2041,
          1.9512888951369312
        ],
        [
          2042,
          1.9630960096199899
        ],
        [
          2043,
          1.9761234800876852
        ],
        [
          2044,
          1.9936852602891426
        ],
        [
          2045,
          2.0107196120978874
        ],
        [
          2046,
          2.0272600124807396
        ],
        [
          2047,
          2.0432843594363668
        ],
        [
          2048,
          2.0587484115421293
        ],
        [
          2049,
          2.0649406499663208
        ],
        [
          2050,
          2.0712759896273365
        ],
        [
          2051,
          2.0775823193511522
        ]
      ]
    },
    {
      "seriesName": "RSD_BLD-XXX_NRGSRV-WS",
      "seriesValues": [
        [
          2018,
          100.82519290272967
        ],
        [
          2019,
          100.10788695001689
        ],
        [
          2020,
          105.23967244465165
        ],
        [
          2021,
          101.29109192324208
        ],
        [
          2022,
          94.34382089187066
        ],
        [
          2023,
          91.36596446797292
        ],
        [
          2024,
          90.30728762203135
        ],
        [
          2025,
          89.18009745345239
        ],
        [
          2026,
          88.02821398154194
        ],
        [
          2027,
          87.49372968350528
        ],
        [
          2028,
          87.49541193522126
        ],
        [
          2029,
          87.33366221125746
        ],
        [
          2030,
          86.67205261872066
        ],
        [
          2031,
          86.93631832681533
        ],
        [
          2032,
          87.22803245326858
        ],
        [
          2033,
          87.34729911322732
        ],
        [
          2034,
          87.55785270457054
        ],
        [
          2035,
          87.98611514960568
        ],
        [
          2036,
          88.41200244639434
        ],
        [
          2037,
          88.8865464651928
        ],
        [
          2038,
          88.76636984023924
        ],
        [
          2039,
          88.65758781423058
        ],
        [
          2040,
          88.48276498254957
        ],
        [
          2041,
          88.23202438087802
        ],
        [
          2042,
          88.07942490808671
        ],
        [
          2043,
          87.96117369872712
        ],
        [
          2044,
          87.83805975413064
        ],
        [
          2045,
          87.70942317825155
        ],
        [
          2046,
          87.57721388937995
        ],
        [
          2047,
          87.44086304386036
        ],
        [
          2048,
          87.30291065062563
        ],
        [
          2049,
          87.16008075513233
        ],
        [
          2050,
          87.01289651899675
        ],
        [
          2051,
          86.85963270900899
        ]
      ]
    }
  ]
}