{
  "name": "bau_macc-tra-green-truck_hev",
  "data": [
    {
      "seriesName": "TRABDL",
      "seriesValues": [
        [
          2018,
          5.96581925535857
        ],
        [
          2019,
          5.91276453189029
        ],
        [
          2020,
          5.12215062137871
        ],
        [
          2021,
          5.59959831924967
        ],
        [
          2022,
          5.77526554471682
        ],
        [
          2023,
          6.12565657973828
        ],
        [
          2024,
          6.40234496070225
        ],
        [
          2025,
          6.40250020848354
        ],
        [
          2026,
          6.41525074456263
        ],
        [
          2027,
          6.3971803442597
        ],
        [
          2028,
          6.4385393918379
        ],
        [
          2029,
          6.53707438815762
        ],
        [
          2030,
          6.65994944832289
        ],
        [
          2031,
          6.65986081915594
        ],
        [
          2032,
          6.74983834251814
        ],
        [
          2033,
          6.96622221608005
        ],
        [
          2034,
          7.20442608145308
        ],
        [
          2035,
          7.39961718777119
        ],
        [
          2036,
          7.57097749262387
        ],
        [
          2037,
          7.80934949753264
        ],
        [
          2038,
          8.04613874598222
        ],
        [
          2039,
          8.26911034622771
        ],
        [
          2040,
          8.46901592921587
        ],
        [
          2041,
          8.6567510618045
        ],
        [
          2042,
          8.82077240462863
        ],
        [
          2043,
          8.96424516787698
        ],
        [
          2044,
          9.08968643512679
        ],
        [
          2045,
          9.22025220149827
        ],
        [
          2046,
          9.32309650128817
        ],
        [
          2047,
          9.41913213609836
        ],
        [
          2048,
          9.53969609488544
        ],
        [
          2049,
          9.66068212510061
        ],
        [
          2050,
          9.76430835214869
        ],
        [
          2051,
          9.76430741575097
        ]
      ]
    },
    {
      "seriesName": "TRACNG",
      "seriesValues": [
        [
          2018,
          1.03707
        ]
      ]
    },
    {
      "seriesName": "TRADST",
      "seriesValues": [
        [
          2018,
          149.145481639395
        ],
        [
          2019,
          144.9207
        ],
        [
          2020,
          123.128611290131
        ],
        [
          2021,
          132.066
        ],
        [
          2022,
          133.686682160401
        ],
        [
          2023,
          139.219467208962
        ],
        [
          2024,
          145.507839674516
        ],
        [
          2025,
          145.511368352719
        ],
        [
          2026,
          145.801152575984
        ],
        [
          2027,
          145.390455437539
        ],
        [
          2028,
          146.330425395015
        ],
        [
          2029,
          148.569868699294
        ],
        [
          2030,
          151.362486934329
        ],
        [
          2031,
          151.046020149839
        ],
        [
          2032,
          153.405414967928
        ],
        [
          2033,
          158.323229847744
        ],
        [
          2034,
          163.736953579254
        ],
        [
          2035,
          168.173114507947
        ],
        [
          2036,
          172.067666298084
        ],
        [
          2037,
          177.485210984771
        ],
        [
          2038,
          182.866785942449
        ],
        [
          2039,
          187.934321891478
        ],
        [
          2040,
          192.477630079998
        ],
        [
          2041,
          196.744337462406
        ],
        [
          2042,
          200.472095512031
        ],
        [
          2043,
          203.732840040462
        ],
        [
          2044,
          206.583778146338
        ],
        [
          2045,
          209.551182959562
        ],
        [
          2046,
          211.888553952407
        ],
        [
          2047,
          214.071182028162
        ],
        [
          2048,
          216.811273230781
        ],
        [
          2049,
          219.560955631985
        ],
        [
          2050,
          221.916097033502
        ],
        [
          2051,
          221.803265545757
        ]
      ]
    },
    {
      "seriesName": "TRAELC",
      "seriesValues": [
        [
          2018,
          0.3848744084419953
        ],
        [
          2019,
          0.5382000309022789
        ],
        [
          2020,
          0.6727500258471178
        ],
        [
          2021,
          0.74520002827128
        ],
        [
          2022,
          0.7720000246512018
        ],
        [
          2023,
          7.556886569273848
        ],
        [
          2024,
          6.996531875557003
        ],
        [
          2025,
          6.115171013623838
        ],
        [
          2026,
          5.268489728735914
        ],
        [
          2027,
          4.448050302434708
        ],
        [
          2028,
          3.5629931118343325
        ],
        [
          2029,
          2.6559649132864953
        ],
        [
          2030,
          1.3543450325102162
        ],
        [
          2031,
          1.6702943060465276
        ],
        [
          2032,
          1.6992602083172041
        ],
        [
          2033,
          1.6585008117723596
        ],
        [
          2034,
          1.6985168457023283
        ],
        [
          2035,
          1.740490716398985
        ],
        [
          2036,
          1.7743276213928902
        ],
        [
          2037,
          1.7066633236440159
        ],
        [
          2038,
          1.7550807877652046
        ],
        [
          2039,
          1.751509848914482
        ],
        [
          2040,
          1.9179833234890737
        ],
        [
          2041,
          2.0351953423349856
        ],
        [
          2042,
          2.2600966112825907
        ],
        [
          2043,
          2.6170064815098586
        ],
        [
          2044,
          3.1593560669752945
        ],
        [
          2045,
          3.0998860392282532
        ],
        [
          2046,
          3.8995374654189434
        ],
        [
          2047,
          4.920024523923566
        ],
        [
          2048,
          5.6452945861692285
        ],
        [
          2049,
          6.360784430614313
        ],
        [
          2050,
          7.2667610512867595
        ],
        [
          2051,
          9.914777353620506
        ]
      ]
    },
    {
      "seriesName": "TRAETH",
      "seriesValues": [
        [
          2018,
          0.995880001342265
        ],
        [
          2019,
          1.0359619142112
        ],
        [
          2020,
          0.839109963160891
        ],
        [
          2021,
          0.851780993720422
        ],
        [
          2022,
          0.916093807287323
        ],
        [
          2023,
          0.760356556044075
        ],
        [
          2024,
          0.901447377861198
        ],
        [
          2025,
          0.960039545658893
        ],
        [
          2026,
          0.95335717456357
        ],
        [
          2027,
          0.965911352189781
        ],
        [
          2028,
          0.968847257190825
        ],
        [
          2029,
          0.971783159022352
        ],
        [
          2030,
          0.974719060276225
        ],
        [
          2031,
          1.10098246018164
        ],
        [
          2032,
          1.1033251726563
        ],
        [
          2033,
          1.10327541551506
        ],
        [
          2034,
          1.10332505961283
        ],
        [
          2035,
          1.10332504718912
        ],
        [
          2036,
          1.10332508300851
        ],
        [
          2037,
          0.672961235470305
        ],
        [
          2038,
          0.585876271140547
        ],
        [
          2039,
          0.516719993356191
        ],
        [
          2040,
          1.10332513707974
        ],
        [
          2041,
          1.10332513109239
        ],
        [
          2042,
          1.10332512788272
        ],
        [
          2043,
          1.10332511560023
        ],
        [
          2044,
          1.10332510250379
        ],
        [
          2045,
          1.09942604306843
        ],
        [
          2046,
          1.09942610081638
        ],
        [
          2047,
          1.09353224588711
        ],
        [
          2048,
          1.09061840541941
        ],
        [
          2049,
          1.08768251830787
        ],
        [
          2050,
          1.07814904982891
        ],
        [
          2051,
          0.958483303612246
        ]
      ]
    },
    {
      "seriesName": "TRAGSL",
      "seriesValues": [
        [
          2018,
          33.196
        ],
        [
          2019,
          33.8549644472201
        ],
        [
          2020,
          26.89455
        ],
        [
          2021,
          26.7855658848016
        ],
        [
          2022,
          28.2745
        ],
        [
          2023,
          23.0411074608624
        ],
        [
          2024,
          27.3165868455727
        ],
        [
          2025,
          29.0921073938751
        ],
        [
          2026,
          28.8896108508328
        ],
        [
          2027,
          29.2700407878986
        ],
        [
          2028,
          29.3590075907494
        ],
        [
          2029,
          29.4479742907888
        ],
        [
          2030,
          29.5369409885831
        ],
        [
          2031,
          33.3631038663651
        ],
        [
          2032,
          33.4340963628261
        ],
        [
          2033,
          29.9235896860537
        ],
        [
          2034,
          25.8339989690695
        ],
        [
          2035,
          23.5690565997201
        ],
        [
          2036,
          22.7642208770352
        ],
        [
          2037,
          20.3927636112287
        ],
        [
          2038,
          17.7538254252152
        ],
        [
          2039,
          15.6581807293985
        ],
        [
          2040,
          13.2155953253762
        ],
        [
          2041,
          11.603450549184
        ],
        [
          2042,
          10.3538473940024
        ],
        [
          2043,
          9.42492414385163
        ],
        [
          2044,
          8.40657908686837
        ],
        [
          2045,
          7.57686774176614
        ],
        [
          2046,
          6.63280820531426
        ],
        [
          2047,
          5.74938075106221
        ],
        [
          2048,
          4.79295904730729
        ],
        [
          2049,
          3.76460636040775
        ],
        [
          2050,
          2.86382219084825
        ],
        [
          2051,
          1.98905820356526
        ]
      ]
    },
    {
      "seriesName": "TRAKER",
      "seriesValues": [
        [
          2018,
          46.2018569489979
        ],
        [
          2019,
          46.5475887442597
        ],
        [
          2020,
          16.5525999456243
        ],
        [
          2021,
          18.464972504151
        ],
        [
          2022,
          47.6285870438932
        ],
        [
          2023,
          48.0889265194245
        ],
        [
          2024,
          48.5324802867636
        ],
        [
          2025,
          48.959711998297
        ],
        [
          2026,
          49.3710727034754
        ],
        [
          2027,
          49.7670011620786
        ],
        [
          2028,
          50.1479241834723
        ],
        [
          2029,
          50.5142569657304
        ],
        [
          2030,
          50.8664033980936
        ],
        [
          2031,
          51.2858407666547
        ],
        [
          2032,
          51.6925093798075
        ],
        [
          2033,
          52.0867149357589
        ],
        [
          2034,
          52.4687559372637
        ],
        [
          2035,
          52.8389239081418
        ],
        [
          2036,
          53.1975035066498
        ],
        [
          2037,
          53.5447727246099
        ],
        [
          2038,
          53.8810030396911
        ],
        [
          2039,
          54.2064595352472
        ],
        [
          2040,
          54.5214011167525
        ],
        [
          2041,
          54.826080584294
        ],
        [
          2042,
          55.1207448421864
        ],
        [
          2043,
          55.40563499353
        ],
        [
          2044,
          55.680986488157
        ],
        [
          2045,
          55.9470292763314
        ],
        [
          2046,
          56.2039879148132
        ],
        [
          2047,
          56.4520816900377
        ],
        [
          2048,
          56.6915247721861
        ],
        [
          2049,
          56.9225263021094
        ],
        [
          2050,
          57.145290550709
        ],
        [
          2051,
          57.4903806500274
        ]
      ]
    },
    {
      "seriesName": "TRAH2",
      "seriesValues": [
        [
          2030,
          0.0
        ],
        [
          2031,
          0.0
        ],
        [
          2032,
          0.0
        ],
        [
          2033,
          0.0
        ],
        [
          2034,
          0.0
        ],
        [
          2035,
          0.0
        ],
        [
          2036,
          0.0
        ],
        [
          2037,
          0.0
        ],
        [
          2038,
          0.0
        ],
        [
          2039,
          0.0
        ],
        [
          2040,
          0.0
        ],
        [
          2041,
          0.0
        ],
        [
          2042,
          3.8820411453746e-06
        ],
        [
          2043,
          7.13692921002369e-06
        ],
        [
          2044,
          0.100098024640559
        ],
        [
          2045,
          0.208124252307804
        ],
        [
          2046,
          0.320906305766252
        ],
        [
          2047,
          0.500651402844952
        ],
        [
          2048,
          0.623941422520234
        ],
        [
          2049,
          0.731128650010178
        ],
        [
          2050,
          0.809741742155065
        ],
        [
          2051,
          1.25086047161972
        ]
      ]
    },
    {
      "seriesName": "TRABJK",
      "seriesValues": [
        [
          2047,
          0.0
        ],
        [
          2048,
          0.0
        ],
        [
          2049,
          0.0
        ],
        [
          2050,
          0.0
        ],
        [
          2051,
          0.0
        ]
      ]
    }
  ]
}